{
  "_fv": 24,
  "_type": "food",
  "definition": {
    "renderType": 0,
    "texture": "sweet_anemone_pie",
    "customModelName": "Normal",
    "name": "Sweet Anemone Pie",
    "rarity": "COMMON",
    "specialInfo": [],
    "creativeTab": {
      "value": "FOOD"
    },
    "stackSize": 64,
    "nutritionalValue": 6,
    "saturation": 6.0,
    "eatingSpeed": 32,
    "resultItem": {
      "value": ""
    },
    "forDogs": false,
    "isAlwaysEdible": false,
    "animation": "eat",
    "hasGlow": false,
    "onEaten": {
      "name": "SweetAnemonePieFoodEaten"
    }
  }
}